HPW_Tracing/__init__.py
HPW_Tracing/config.py
HPW_Tracing/Build_graphs/__init__.py
HPW_Tracing/Build_graphs/build_sub_graph.py
HPW_Tracing/Build_graphs/make_graph.py
HPW_Tracing/Build_graphs/network_correction.py
HPW_Tracing/Load_data/__init__.py
HPW_Tracing/Load_data/load_data.py
HPW_Tracing/Tracing/Tracing_with_distance.py
HPW_Tracing/Tracing/__init__.py
HPW_Tracing/Tracing/mh_name_ufid_lookup.py
HPW_Tracing-0.3.3.dist-info/METADATA
HPW_Tracing-0.3.3.dist-info/WHEEL
HPW_Tracing-0.3.3.dist-info/top_level.txt
HPW_Tracing-0.3.3.dist-info/RECORD
