Metadata-Version: 2.1
Name: HPW-Tracing
Version: 0.3.3
Author: Peng Xie
Author-email: xphn1985@gmail.com
License: MIT
Classifier: License :: OSI Approved :: MIT License
Classifier: Programming Language :: Python :: 3.11
Classifier: Operating System :: OS Independent
Requires-Python: >=3.9
Requires-Dist: geopandas ~=0.14.3
Requires-Dist: networkx ~=3.2.1
Requires-Dist: pandas ~=2.2.1
Requires-Dist: setuptools ~=68.2.2
Requires-Dist: Shapely ~=2.0.3
Requires-Dist: config ~=0.5.1
Requires-Dist: notebook ~=6.4.3
